
 [

    {
       "id":"1",
        "routeNo": "602", 
        "from":"nyamirambo",
        "to": "town",
        "noOfStations":"4",
        "stations": "mrez"
        
        ,"price": "300"}
           ,

    { 
        "id":"2",
        "routeNo": "702",
        "from": "Remera",
       " to": "kimisagara",
        "noOfStations": "6", 
        "stations": "kobil", 
        "price": "500" },

    {
    "id":"3", 
    "routeNo": "502",
    "from": "nyabugogo",
    "to": "town", 
    "noOfStations": "3",
    "stations": "mrez",
    "price": "245" }



]
